evolvishub_text_classification_llm/__init__.py
evolvishub_text_classification_llm/core/__init__.py
evolvishub_text_classification_llm/core/config.py
evolvishub_text_classification_llm/core/exceptions.py
evolvishub_text_classification_llm/core/interfaces.py
evolvishub_text_classification_llm/core/schemas.py
evolvishub_text_classification_llm/monitoring/__init__.py
evolvishub_text_classification_llm/monitoring/health.py
evolvishub_text_classification_llm/monitoring/metrics.py
evolvishub_text_classification_llm/providers/__init__.py
evolvishub_text_classification_llm/providers/anthropic.py
evolvishub_text_classification_llm/providers/aws_bedrock.py
evolvishub_text_classification_llm/providers/azure_openai.py
evolvishub_text_classification_llm/providers/base.py
evolvishub_text_classification_llm/providers/cohere.py
evolvishub_text_classification_llm/providers/custom.py
evolvishub_text_classification_llm/providers/factory.py
evolvishub_text_classification_llm/providers/google.py
evolvishub_text_classification_llm/providers/huggingface.py
evolvishub_text_classification_llm/providers/mistral.py
evolvishub_text_classification_llm/providers/ollama.py
evolvishub_text_classification_llm/providers/openai.py
evolvishub_text_classification_llm/providers/replicate.py
evolvishub_text_classification_llm/streaming/__init__.py
evolvishub_text_classification_llm/streaming/engine.py
evolvishub_text_classification_llm/streaming/schemas.py
evolvishub_text_classification_llm/workflows/__init__.py
evolvishub_text_classification_llm/workflows/base.py
evolvishub_text_classification_llm/workflows/batch.py
evolvishub_text_classification_llm/workflows/classification.py
evolvishub_text_classification_llm-1.1.0.dist-info/licenses/LICENSE
evolvishub_text_classification_llm-1.1.0.dist-info/METADATA
evolvishub_text_classification_llm-1.1.0.dist-info/WHEEL
evolvishub_text_classification_llm-1.1.0.dist-info/entry_points.txt
evolvishub_text_classification_llm-1.1.0.dist-info/top_level.txt
evolvishub_text_classification_llm-1.1.0.dist-info/RECORD
