Metadata-Version: 2.4
Name: evolvishub-text-classification-llm
Version: 1.1.0
Summary: Enterprise-grade text classification library with 11+ LLM providers, streaming, monitoring, and advanced workflows
Home-page: https://github.com/evolvishub/text-classification-llm
Author: Alban Maxhuni, PhD
Author-email: "Alban Maxhuni, PhD" <a.maxhuni@evolvis.ai>
License: Proprietary
Project-URL: Homepage, https://evolvis.ai
Project-URL: Documentation, https://docs.evolvis.ai/text-classification-llm
Project-URL: Repository, https://github.com/evolvisai/metcal
Project-URL: Bug Tracker, https://github.com/evolvisai/metcal/issues
Project-URL: Changelog, https://github.com/evolvisai/metcal/blob/main/shared/libs/evolvishub-text-classification-llm/CHANGELOG.md
Project-URL: Company, https://evolvis.ai
Keywords: text-classification,llm,nlp,machine-learning,ai,openai,anthropic,google,huggingface,transformers,gpt,claude,gemini,cohere,mistral,replicate,azure,aws,bedrock,ollama,enterprise,proprietary,evolvis,async,batch-processing,streaming,real-time,workflows,monitoring,health-checks,metrics,professional
Classifier: Development Status :: 5 - Production/Stable
Classifier: Intended Audience :: Developers
Classifier: Intended Audience :: Science/Research
Classifier: Intended Audience :: Information Technology
Classifier: License :: Other/Proprietary License
Classifier: Operating System :: OS Independent
Classifier: Programming Language :: Python :: 3
Classifier: Programming Language :: Python :: 3.9
Classifier: Programming Language :: Python :: 3.10
Classifier: Programming Language :: Python :: 3.11
Classifier: Programming Language :: Python :: 3.12
Classifier: Topic :: Scientific/Engineering :: Artificial Intelligence
Classifier: Topic :: Software Development :: Libraries :: Python Modules
Classifier: Topic :: Text Processing :: Linguistic
Classifier: Topic :: Office/Business :: Financial :: Investment
Classifier: Framework :: AsyncIO
Classifier: Framework :: Pydantic
Classifier: Framework :: FastAPI
Requires-Python: >=3.9
License-File: LICENSE
Requires-Dist: pydantic>=2.8.0
Requires-Dist: asyncio-throttle>=1.0.2
Requires-Dist: aiofiles>=24.1.0
Requires-Dist: httpx>=0.27.0
Requires-Dist: pyyaml>=6.0.2
Requires-Dist: python-dateutil>=2.9.0
Requires-Dist: numpy>=1.26.0
Requires-Dist: jsonschema>=4.23.0
Provides-Extra: openai
Requires-Dist: openai>=1.40.0; extra == "openai"
Provides-Extra: anthropic
Requires-Dist: anthropic>=0.34.0; extra == "anthropic"
Provides-Extra: google
Requires-Dist: google-generativeai>=0.7.2; extra == "google"
Provides-Extra: cohere
Requires-Dist: cohere>=5.5.0; extra == "cohere"
Provides-Extra: azure-openai
Requires-Dist: openai>=1.40.0; extra == "azure-openai"
Requires-Dist: azure-identity>=1.17.0; extra == "azure-openai"
Provides-Extra: aws-bedrock
Requires-Dist: boto3>=1.35.0; extra == "aws-bedrock"
Requires-Dist: botocore>=1.35.0; extra == "aws-bedrock"
Provides-Extra: huggingface
Requires-Dist: transformers>=4.44.0; extra == "huggingface"
Requires-Dist: torch>=2.4.0; extra == "huggingface"
Requires-Dist: accelerate>=0.33.0; extra == "huggingface"
Requires-Dist: bitsandbytes>=0.43.0; extra == "huggingface"
Requires-Dist: sentencepiece>=0.2.0; extra == "huggingface"
Provides-Extra: ollama
Requires-Dist: aiohttp>=3.9.0; extra == "ollama"
Provides-Extra: mistral
Requires-Dist: mistralai>=1.0.0; extra == "mistral"
Provides-Extra: replicate
Requires-Dist: replicate>=0.25.0; extra == "replicate"
Provides-Extra: custom
Requires-Dist: aiohttp>=3.9.0; extra == "custom"
Provides-Extra: cloud
Requires-Dist: openai>=1.40.0; extra == "cloud"
Requires-Dist: anthropic>=0.34.0; extra == "cloud"
Requires-Dist: google-generativeai>=0.7.2; extra == "cloud"
Requires-Dist: cohere>=5.5.0; extra == "cloud"
Requires-Dist: mistralai>=1.0.0; extra == "cloud"
Requires-Dist: replicate>=0.25.0; extra == "cloud"
Provides-Extra: local
Requires-Dist: transformers>=4.44.0; extra == "local"
Requires-Dist: torch>=2.4.0; extra == "local"
Requires-Dist: accelerate>=0.33.0; extra == "local"
Requires-Dist: ollama>=0.3.0; extra == "local"
Provides-Extra: enterprise
Requires-Dist: openai>=1.40.0; extra == "enterprise"
Requires-Dist: azure-identity>=1.17.0; extra == "enterprise"
Requires-Dist: boto3>=1.35.0; extra == "enterprise"
Requires-Dist: botocore>=1.35.0; extra == "enterprise"
Provides-Extra: workflows
Requires-Dist: langgraph>=0.2.0; extra == "workflows"
Requires-Dist: langchain-core>=0.2.0; extra == "workflows"
Requires-Dist: langchain-community>=0.2.0; extra == "workflows"
Provides-Extra: streaming
Requires-Dist: websockets>=12.0; extra == "streaming"
Requires-Dist: fastapi>=0.111.0; extra == "streaming"
Requires-Dist: uvicorn>=0.30.0; extra == "streaming"
Provides-Extra: monitoring
Requires-Dist: prometheus-client>=0.20.0; extra == "monitoring"
Requires-Dist: structlog>=24.2.0; extra == "monitoring"
Requires-Dist: psutil>=6.0.0; extra == "monitoring"
Provides-Extra: caching
Requires-Dist: redis>=5.0.7; extra == "caching"
Requires-Dist: diskcache>=5.6.3; extra == "caching"
Requires-Dist: faiss-cpu>=1.8.0; extra == "caching"
Requires-Dist: sentence-transformers>=3.0.0; extra == "caching"
Provides-Extra: security
Requires-Dist: cryptography>=43.0.0; extra == "security"
Requires-Dist: bleach>=6.1.0; extra == "security"
Provides-Extra: finetuning
Requires-Dist: datasets>=2.20.0; extra == "finetuning"
Requires-Dist: evaluate>=0.4.0; extra == "finetuning"
Requires-Dist: peft>=0.12.0; extra == "finetuning"
Provides-Extra: multimodal
Requires-Dist: pillow>=10.4.0; extra == "multimodal"
Requires-Dist: opencv-python>=4.10.0; extra == "multimodal"
Requires-Dist: pytesseract>=0.3.10; extra == "multimodal"
Provides-Extra: all
Requires-Dist: openai>=1.40.0; extra == "all"
Requires-Dist: anthropic>=0.34.0; extra == "all"
Requires-Dist: google-generativeai>=0.7.2; extra == "all"
Requires-Dist: cohere>=5.5.0; extra == "all"
Requires-Dist: mistralai>=1.0.0; extra == "all"
Requires-Dist: replicate>=0.25.0; extra == "all"
Requires-Dist: azure-identity>=1.17.0; extra == "all"
Requires-Dist: boto3>=1.35.0; extra == "all"
Requires-Dist: botocore>=1.35.0; extra == "all"
Requires-Dist: transformers>=4.44.0; extra == "all"
Requires-Dist: torch>=2.4.0; extra == "all"
Requires-Dist: accelerate>=0.33.0; extra == "all"
Requires-Dist: bitsandbytes>=0.43.0; extra == "all"
Requires-Dist: sentencepiece>=0.2.0; extra == "all"
Requires-Dist: aiohttp>=3.9.0; extra == "all"
Requires-Dist: langgraph>=0.2.0; extra == "all"
Requires-Dist: langchain-core>=0.2.0; extra == "all"
Requires-Dist: langchain-community>=0.2.0; extra == "all"
Requires-Dist: websockets>=12.0; extra == "all"
Requires-Dist: fastapi>=0.111.0; extra == "all"
Requires-Dist: uvicorn>=0.30.0; extra == "all"
Requires-Dist: prometheus-client>=0.20.0; extra == "all"
Requires-Dist: structlog>=24.2.0; extra == "all"
Requires-Dist: psutil>=6.0.0; extra == "all"
Requires-Dist: redis>=5.0.7; extra == "all"
Requires-Dist: diskcache>=5.6.3; extra == "all"
Requires-Dist: faiss-cpu>=1.8.0; extra == "all"
Requires-Dist: sentence-transformers>=3.0.0; extra == "all"
Requires-Dist: cryptography>=43.0.0; extra == "all"
Requires-Dist: bleach>=6.1.0; extra == "all"
Requires-Dist: datasets>=2.20.0; extra == "all"
Requires-Dist: evaluate>=0.4.0; extra == "all"
Requires-Dist: peft>=0.12.0; extra == "all"
Requires-Dist: pillow>=10.4.0; extra == "all"
Requires-Dist: opencv-python>=4.10.0; extra == "all"
Requires-Dist: pytesseract>=0.3.10; extra == "all"
Provides-Extra: dev
Requires-Dist: openai>=1.40.0; extra == "dev"
Requires-Dist: anthropic>=0.34.0; extra == "dev"
Requires-Dist: google-generativeai>=0.7.2; extra == "dev"
Requires-Dist: cohere>=5.5.0; extra == "dev"
Requires-Dist: mistralai>=1.0.0; extra == "dev"
Requires-Dist: replicate>=0.25.0; extra == "dev"
Requires-Dist: azure-identity>=1.17.0; extra == "dev"
Requires-Dist: boto3>=1.35.0; extra == "dev"
Requires-Dist: transformers>=4.44.0; extra == "dev"
Requires-Dist: torch>=2.4.0; extra == "dev"
Requires-Dist: aiohttp>=3.9.0; extra == "dev"
Requires-Dist: langgraph>=0.2.0; extra == "dev"
Requires-Dist: websockets>=12.0; extra == "dev"
Requires-Dist: fastapi>=0.111.0; extra == "dev"
Requires-Dist: prometheus-client>=0.20.0; extra == "dev"
Requires-Dist: redis>=5.0.7; extra == "dev"
Requires-Dist: faiss-cpu>=1.8.0; extra == "dev"
Requires-Dist: sentence-transformers>=3.0.0; extra == "dev"
Requires-Dist: cryptography>=43.0.0; extra == "dev"
Requires-Dist: datasets>=2.20.0; extra == "dev"
Requires-Dist: peft>=0.12.0; extra == "dev"
Requires-Dist: pillow>=10.4.0; extra == "dev"
Requires-Dist: pytest>=8.3.0; extra == "dev"
Requires-Dist: pytest-asyncio>=0.23.0; extra == "dev"
Requires-Dist: pytest-mock>=3.14.0; extra == "dev"
Requires-Dist: pytest-cov>=5.0.0; extra == "dev"
Requires-Dist: pytest-benchmark>=4.0.0; extra == "dev"
Requires-Dist: black>=24.8.0; extra == "dev"
Requires-Dist: isort>=5.13.0; extra == "dev"
Requires-Dist: flake8>=7.1.0; extra == "dev"
Requires-Dist: mypy>=1.11.0; extra == "dev"
Requires-Dist: pre-commit>=3.8.0; extra == "dev"
Requires-Dist: sphinx>=8.0.0; extra == "dev"
Requires-Dist: sphinx-rtd-theme>=2.0.0; extra == "dev"
Requires-Dist: jupyter>=1.1.0; extra == "dev"
Requires-Dist: pandas>=2.2.0; extra == "dev"
Dynamic: author
Dynamic: home-page
Dynamic: license-file
Dynamic: requires-python
